trusd/__init__.py
trusd/cli.py
trusd/plot.py
trusd/problemfil.py
trusd/simulate.py
trusd/test.py
trusd/trusd.py
TruSD-0.0.6.dist-info/LICENSE
TruSD-0.0.6.dist-info/METADATA
TruSD-0.0.6.dist-info/WHEEL
TruSD-0.0.6.dist-info/entry_points.txt
TruSD-0.0.6.dist-info/top_level.txt
TruSD-0.0.6.dist-info/RECORD
