Metadata-Version: 2.1
Name: TruSD
Version: 0.0.6
Summary: TruSD co-infers selection coefficients and genetic drift from allele trajectories using a maximum-likelihood framework.
Home-page: https://github.com/mathiasbockwoldt/TruSD
Author: Mathias Bockwoldt
Author-email: mathias.bockwoldt@gmail.com
License: UNKNOWN
Platform: UNKNOWN
Classifier: Programming Language :: Python :: 3 :: Only
Classifier: Programming Language :: Python :: 3.6
Classifier: Programming Language :: Python :: 3.7
Classifier: Programming Language :: Python :: 3.8
Classifier: Programming Language :: Python :: 3.9
Classifier: Programming Language :: Python :: 3.10
Classifier: License :: OSI Approved :: MIT License
Classifier: Operating System :: OS Independent
Classifier: Development Status :: 4 - Beta
Classifier: Intended Audience :: Science/Research
Classifier: Natural Language :: English
Classifier: Topic :: Scientific/Engineering :: Bio-Informatics
Requires-Python: >=3.6
License-File: LICENSE
Requires-Dist: numpy (>=1.15.1)
Requires-Dist: scipy (>=0.16.0)
Requires-Dist: matplotlib (>=3.1.1)
